duat/__init__.py
duat/common.py
duat/osiris/__init__.py
duat/osiris/config.py
duat/osiris/plot.py
duat/osiris/run.py
duat-0.1.0.dist-info/DESCRIPTION.rst
duat-0.1.0.dist-info/METADATA
duat-0.1.0.dist-info/RECORD
duat-0.1.0.dist-info/WHEEL
duat-0.1.0.dist-info/entry_points.txt
duat-0.1.0.dist-info/metadata.json
duat-0.1.0.dist-info/top_level.txt
