Metadata-Version: 2.0
Name: duat
Version: 0.1.0
Summary: A python interface to the Osiris PiC code
Home-page: https://github.com/dih5/duat
Author: Dih5
Author-email: guillehg@gmail.com
License: MIT
Keywords: Particle in Cell,plasma physics
Platform: UNKNOWN
Classifier: Development Status :: 3 - Alpha
Classifier: Intended Audience :: Science/Research
Classifier: Topic :: Scientific/Engineering :: Physics
Classifier: License :: OSI Approved :: MIT License
Classifier: Programming Language :: Python :: 2
Classifier: Programming Language :: Python :: 2.6
Classifier: Programming Language :: Python :: 2.7
Classifier: Programming Language :: Python :: 3
Classifier: Programming Language :: Python :: 3.3
Classifier: Programming Language :: Python :: 3.4
Classifier: Programming Language :: Python :: 3.5
Requires-Dist: future
Requires-Dist: h5py
Requires-Dist: matplotlib
Requires-Dist: numpy
Provides-Extra: demos
Provides-Extra: dev
Provides-Extra: docs
Requires-Dist: sphinx-rtd-theme; extra == 'docs'
Provides-Extra: test
